
[
  {
    "user_id": 1,
    "firstName": "Pete",
    "lastName": "Smith",
    "email": "peter.appliedanalyticalsciences@gmail.com",
    "zipcode": "34695",
    "specialty": "Composition",
    "region": "Tampa FL",
    "phone": "603-801-9877",
    "virtual": "Virtual or In Person",
    "instruments": "guitar",
    "profile_pic": "Guitar 3"
  },
  {
    "user_id": 2,
    "firstName": "Stephanie",
    "lastName": "Carr",
    "email": "instructor-1@gmail.com",
    "zipcode": "34695",
    "specialty": "Strings Stage Performance / Orchestra",
    "region": "St Pete FL",
    "phone": null,
    "virtual": "Virtual or In Person",
    "instruments": "Cello",
    "profile_pic": "Cello 2"
  }
]


